<?xml version="1.0" encoding="utf-8"?>
<annotation>
	<filename>0000599.jpg</filename>
	<folder>BLR-2018-06-19-06-21-44_part_52_1</folder>
	<size>
		<width>1921</width>
		<height>1080</height>
		<depth>3</depth>
	</size>
	<object>
		<name>motorcycle</name>
		<bndbox>
			<xmin>897</xmin>
			<ymax>584</ymax>
			<xmax>909</xmax>
			<ymin>567</ymin>
		</bndbox>
	</object>
	<object>
		<name>rider</name>
		<bndbox>
			<xmin>897</xmin>
			<ymax>580</ymax>
			<xmax>911</xmax>
			<ymin>557</ymin>
		</bndbox>
	</object>
	<object>
		<name>motorcycle</name>
		<bndbox>
			<xmin>904</xmin>
			<ymax>599</ymax>
			<xmax>921</xmax>
			<ymin>569</ymin>
		</bndbox>
	</object>
	<object>
		<name>rider</name>
		<bndbox>
			<xmin>903</xmin>
			<ymax>595</ymax>
			<xmax>922</xmax>
			<ymin>559</ymin>
		</bndbox>
	</object>
	<object>
		<name>vehicle fallback</name>
		<bndbox>
			<xmin>925</xmin>
			<ymax>571</ymax>
			<xmax>936</xmax>
			<ymin>552</ymin>
		</bndbox>
	</object>
	<object>
		<name>truck</name>
		<bndbox>
			<xmin>931</xmin>
			<ymax>582</ymax>
			<xmax>956</xmax>
			<ymin>546</ymin>
		</bndbox>
	</object>
	<object>
		<name>car</name>
		<bndbox>
			<xmin>952</xmin>
			<ymax>575</ymax>
			<xmax>965</xmax>
			<ymin>560</ymin>
		</bndbox>
	</object>
	<object>
		<name>car</name>
		<bndbox>
			<xmin>960</xmin>
			<ymax>576</ymax>
			<xmax>978</xmax>
			<ymin>557</ymin>
		</bndbox>
	</object>
	<object>
		<name>car</name>
		<bndbox>
			<xmin>970</xmin>
			<ymax>577</ymax>
			<xmax>987</xmax>
			<ymin>561</ymin>
		</bndbox>
	</object>
	<object>
		<name>car</name>
		<bndbox>
			<xmin>984</xmin>
			<ymax>582</ymax>
			<xmax>1008</xmax>
			<ymin>561</ymin>
		</bndbox>
	</object>
	<object>
		<name>bus</name>
		<bndbox>
			<xmin>1012</xmin>
			<ymax>592</ymax>
			<xmax>1097</xmax>
			<ymin>537</ymin>
		</bndbox>
	</object>
	<object>
		<name>vehicle fallback</name>
		<bndbox>
			<xmin>1086</xmin>
			<ymax>588</ymax>
			<xmax>1108</xmax>
			<ymin>549</ymin>
		</bndbox>
	</object>
	<object>
		<name>autorickshaw</name>
		<bndbox>
			<xmin>839</xmin>
			<ymax>607</ymax>
			<xmax>876</xmax>
			<ymin>561</ymin>
		</bndbox>
	</object>
	<object>
		<name>truck</name>
		<bndbox>
			<xmin>1075</xmin>
			<ymax>935</ymax>
			<xmax>1921</xmax>
			<ymin>208</ymin>
		</bndbox>
	</object>
</annotation>