<?xml version="1.0" encoding="utf-8"?>
<annotation>
	<filename>0005876.jpg</filename>
	<folder>HYD-2018-08-24_13-02-50_9</folder>
	<size>
		<width>1920</width>
		<height>1080</height>
		<depth>3</depth>
	</size>
	<object>
		<name>motorcycle</name>
		<bndbox>
			<xmin>445</xmin>
			<ymax>658</ymax>
			<xmax>528</xmax>
			<ymin>577</ymin>
		</bndbox>
	</object>
	<object>
		<name>motorcycle</name>
		<bndbox>
			<xmin>369</xmin>
			<ymax>677</ymax>
			<xmax>503</xmax>
			<ymin>583</ymin>
		</bndbox>
	</object>
	<object>
		<name>motorcycle</name>
		<bndbox>
			<xmin>255</xmin>
			<ymax>720</ymax>
			<xmax>436</xmax>
			<ymin>572</ymin>
		</bndbox>
	</object>
	<object>
		<name>truck</name>
		<bndbox>
			<xmin>0</xmin>
			<ymax>955</ymax>
			<xmax>220</xmax>
			<ymin>494</ymin>
		</bndbox>
	</object>
	<object>
		<name>person</name>
		<bndbox>
			<xmin>522</xmin>
			<ymax>612</ymax>
			<xmax>549</xmax>
			<ymin>551</ymin>
		</bndbox>
	</object>
	<object>
		<name>truck</name>
		<bndbox>
			<xmin>506</xmin>
			<ymax>776</ymax>
			<xmax>832</xmax>
			<ymin>510</ymin>
		</bndbox>
	</object>
	<object>
		<name>truck</name>
		<bndbox>
			<xmin>826</xmin>
			<ymax>658</ymax>
			<xmax>906</xmax>
			<ymin>557</ymin>
		</bndbox>
	</object>
	<object>
		<name>motorcycle</name>
		<bndbox>
			<xmin>832</xmin>
			<ymax>667</ymax>
			<xmax>887</xmax>
			<ymin>610</ymin>
		</bndbox>
	</object>
	<object>
		<name>rider</name>
		<bndbox>
			<xmin>832</xmin>
			<ymax>668</ymax>
			<xmax>873</xmax>
			<ymin>578</ymin>
		</bndbox>
	</object>
	<object>
		<name>motorcycle</name>
		<bndbox>
			<xmin>1013</xmin>
			<ymax>592</ymax>
			<xmax>1048</xmax>
			<ymin>575</ymin>
		</bndbox>
	</object>
	<object>
		<name>truck</name>
		<bndbox>
			<xmin>913</xmin>
			<ymax>623</ymax>
			<xmax>1006</xmax>
			<ymin>506</ymin>
		</bndbox>
	</object>
	<object>
		<name>motorcycle</name>
		<bndbox>
			<xmin>1014</xmin>
			<ymax>593</ymax>
			<xmax>1049</xmax>
			<ymin>574</ymin>
		</bndbox>
	</object>
	<object>
		<name>motorcycle</name>
		<bndbox>
			<xmin>1004</xmin>
			<ymax>587</ymax>
			<xmax>1018</xmax>
			<ymin>573</ymin>
		</bndbox>
	</object>
	<object>
		<name>car</name>
		<bndbox>
			<xmin>1086</xmin>
			<ymax>581</ymax>
			<xmax>1103</xmax>
			<ymin>563</ymin>
		</bndbox>
	</object>
	<object>
		<name>vehicle fallback</name>
		<bndbox>
			<xmin>1107</xmin>
			<ymax>579</ymax>
			<xmax>1128</xmax>
			<ymin>559</ymin>
		</bndbox>
	</object>
	<object>
		<name>car</name>
		<bndbox>
			<xmin>1105</xmin>
			<ymax>579</ymax>
			<xmax>1124</xmax>
			<ymin>566</ymin>
		</bndbox>
	</object>
	<object>
		<name>car</name>
		<bndbox>
			<xmin>1095</xmin>
			<ymax>595</ymax>
			<xmax>1126</xmax>
			<ymin>571</ymin>
		</bndbox>
	</object>
	<object>
		<name>person</name>
		<bndbox>
			<xmin>1123</xmin>
			<ymax>583</ymax>
			<xmax>1129</xmax>
			<ymin>565</ymin>
		</bndbox>
	</object>
	<object>
		<name>vehicle fallback</name>
		<bndbox>
			<xmin>1167</xmin>
			<ymax>571</ymax>
			<xmax>1179</xmax>
			<ymin>554</ymin>
		</bndbox>
	</object>
	<object>
		<name>vehicle fallback</name>
		<bndbox>
			<xmin>1151</xmin>
			<ymax>569</ymax>
			<xmax>1163</xmax>
			<ymin>555</ymin>
		</bndbox>
	</object>
	<object>
		<name>vehicle fallback</name>
		<bndbox>
			<xmin>1148</xmin>
			<ymax>570</ymax>
			<xmax>1158</xmax>
			<ymin>561</ymin>
		</bndbox>
	</object>
	<object>
		<name>vehicle fallback</name>
		<bndbox>
			<xmin>1133</xmin>
			<ymax>571</ymax>
			<xmax>1148</xmax>
			<ymin>561</ymin>
		</bndbox>
	</object>
	<object>
		<name>vehicle fallback</name>
		<bndbox>
			<xmin>1126</xmin>
			<ymax>575</ymax>
			<xmax>1139</xmax>
			<ymin>566</ymin>
		</bndbox>
	</object>
	<object>
		<name>motorcycle</name>
		<bndbox>
			<xmin>1156</xmin>
			<ymax>578</ymax>
			<xmax>1161</xmax>
			<ymin>571</ymin>
		</bndbox>
	</object>
	<object>
		<name>rider</name>
		<bndbox>
			<xmin>1156</xmin>
			<ymax>577</ymax>
			<xmax>1162</xmax>
			<ymin>565</ymin>
		</bndbox>
	</object>
	<object>
		<name>motorcycle</name>
		<bndbox>
			<xmin>1138</xmin>
			<ymax>579</ymax>
			<xmax>1145</xmax>
			<ymin>571</ymin>
		</bndbox>
	</object>
	<object>
		<name>rider</name>
		<bndbox>
			<xmin>1138</xmin>
			<ymax>578</ymax>
			<xmax>1145</xmax>
			<ymin>566</ymin>
		</bndbox>
	</object>
	<object>
		<name>vehicle fallback</name>
		<bndbox>
			<xmin>1209</xmin>
			<ymax>572</ymax>
			<xmax>1220</xmax>
			<ymin>562</ymin>
		</bndbox>
	</object>
	<object>
		<name>vehicle fallback</name>
		<bndbox>
			<xmin>1222</xmin>
			<ymax>583</ymax>
			<xmax>1241</xmax>
			<ymin>560</ymin>
		</bndbox>
	</object>
	<object>
		<name>autorickshaw</name>
		<bndbox>
			<xmin>1237</xmin>
			<ymax>592</ymax>
			<xmax>1259</xmax>
			<ymin>568</ymin>
		</bndbox>
	</object>
	<object>
		<name>motorcycle</name>
		<bndbox>
			<xmin>1270</xmin>
			<ymax>588</ymax>
			<xmax>1280</xmax>
			<ymin>574</ymin>
		</bndbox>
	</object>
	<object>
		<name>rider</name>
		<bndbox>
			<xmin>1272</xmin>
			<ymax>586</ymax>
			<xmax>1280</xmax>
			<ymin>569</ymin>
		</bndbox>
	</object>
	<object>
		<name>vehicle fallback</name>
		<bndbox>
			<xmin>1341</xmin>
			<ymax>599</ymax>
			<xmax>1380</xmax>
			<ymin>519</ymin>
		</bndbox>
	</object>
	<object>
		<name>truck</name>
		<bndbox>
			<xmin>1398</xmin>
			<ymax>614</ymax>
			<xmax>1478</xmax>
			<ymin>554</ymin>
		</bndbox>
	</object>
	<object>
		<name>motorcycle</name>
		<bndbox>
			<xmin>1466</xmin>
			<ymax>636</ymax>
			<xmax>1492</xmax>
			<ymin>604</ymin>
		</bndbox>
	</object>
	<object>
		<name>rider</name>
		<bndbox>
			<xmin>1471</xmin>
			<ymax>634</ymax>
			<xmax>1495</xmax>
			<ymin>588</ymin>
		</bndbox>
	</object>
	<object>
		<name>motorcycle</name>
		<bndbox>
			<xmin>1554</xmin>
			<ymax>641</ymax>
			<xmax>1570</xmax>
			<ymin>615</ymin>
		</bndbox>
	</object>
	<object>
		<name>truck</name>
		<bndbox>
			<xmin>1563</xmin>
			<ymax>653</ymax>
			<xmax>1711</xmax>
			<ymin>546</ymin>
		</bndbox>
	</object>
	<object>
		<name>autorickshaw</name>
		<bndbox>
			<xmin>1813</xmin>
			<ymax>701</ymax>
			<xmax>1918</xmax>
			<ymin>592</ymin>
		</bndbox>
	</object>
	<object>
		<name>traffic sign</name>
		<bndbox>
			<xmin>1538</xmin>
			<ymax>750</ymax>
			<xmax>1553</xmax>
			<ymin>733</ymin>
		</bndbox>
	</object>
	<object>
		<name>motorcycle</name>
		<bndbox>
			<xmin>1094</xmin>
			<ymax>631</ymax>
			<xmax>1122</xmax>
			<ymin>592</ymin>
		</bndbox>
	</object>
	<object>
		<name>rider</name>
		<bndbox>
			<xmin>1096</xmin>
			<ymax>625</ymax>
			<xmax>1124</xmax>
			<ymin>573</ymin>
		</bndbox>
	</object>
	<object>
		<name>person</name>
		<bndbox>
			<xmin>1172</xmin>
			<ymax>658</ymax>
			<xmax>1214</xmax>
			<ymin>568</ymin>
		</bndbox>
	</object>
	<object>
		<name>rider</name>
		<bndbox>
			<xmin>1096</xmin>
			<ymax>626</ymax>
			<xmax>1125</xmax>
			<ymin>576</ymin>
		</bndbox>
	</object>
</annotation>