<?xml version="1.0" encoding="utf-8"?>
<annotation>
	<filename>0008925.jpg</filename>
	<folder>BLR-2018-05-03_14-05-29_sideRight_left_7</folder>
	<size>
		<width>1920</width>
		<height>1080</height>
		<depth>3</depth>
	</size>
	<object>
		<name>autorickshaw</name>
		<bndbox>
			<xmin>124</xmin>
			<ymax>539</ymax>
			<xmax>219</xmax>
			<ymin>383</ymin>
		</bndbox>
	</object>
	<object>
		<name>truck</name>
		<bndbox>
			<xmin>1</xmin>
			<ymax>581</ymax>
			<xmax>150</xmax>
			<ymin>250</ymin>
		</bndbox>
	</object>
	<object>
		<name>motorcycle</name>
		<bndbox>
			<xmin>1344</xmin>
			<ymax>564</ymax>
			<xmax>1374</xmax>
			<ymin>523</ymin>
		</bndbox>
	</object>
	<object>
		<name>autorickshaw</name>
		<bndbox>
			<xmin>1347</xmin>
			<ymax>568</ymax>
			<xmax>1394</xmax>
			<ymin>475</ymin>
		</bndbox>
	</object>
	<object>
		<name>person</name>
		<bndbox>
			<xmin>1744</xmin>
			<ymax>618</ymax>
			<xmax>1789</xmax>
			<ymin>482</ymin>
		</bndbox>
	</object>
	<object>
		<name>motorcycle</name>
		<bndbox>
			<xmin>1726</xmin>
			<ymax>634</ymax>
			<xmax>1866</xmax>
			<ymin>524</ymin>
		</bndbox>
	</object>
	<object>
		<name>truck</name>
		<bndbox>
			<xmin>187</xmin>
			<ymax>782</ymax>
			<xmax>1369</xmax>
			<ymin>1</ymin>
		</bndbox>
	</object>
</annotation>