<?xml version="1.0" encoding="utf-8"?>
<annotation>
	<filename>0003480.jpg</filename>
	<folder>BLR-2018-03-22_17-39-26_2_sideRight_right_3</folder>
	<size>
		<width>1920</width>
		<height>1080</height>
		<depth>3</depth>
	</size>
	<object>
		<name>motorcycle</name>
		<bndbox>
			<xmin>2</xmin>
			<ymax>499</ymax>
			<xmax>128</xmax>
			<ymin>356</ymin>
		</bndbox>
	</object>
	<object>
		<name>motorcycle</name>
		<bndbox>
			<xmin>493</xmin>
			<ymax>626</ymax>
			<xmax>854</xmax>
			<ymin>367</ymin>
		</bndbox>
	</object>
	<object>
		<name>rider</name>
		<bndbox>
			<xmin>568</xmin>
			<ymax>595</ymax>
			<xmax>767</xmax>
			<ymin>301</ymin>
		</bndbox>
	</object>
	<object>
		<name>person</name>
		<bndbox>
			<xmin>91</xmin>
			<ymax>396</ymax>
			<xmax>135</xmax>
			<ymin>287</ymin>
		</bndbox>
	</object>
	<object>
		<name>person</name>
		<bndbox>
			<xmin>68</xmin>
			<ymax>405</ymax>
			<xmax>109</xmax>
			<ymin>261</ymin>
		</bndbox>
	</object>
</annotation>