<?xml version="1.0" encoding="utf-8"?>
<annotation>
	<filename>0002460.jpg</filename>
	<folder>BLR-2018-05-07_12-25-41_sideRight_right_1</folder>
	<size>
		<width>1920</width>
		<height>1080</height>
		<depth>3</depth>
	</size>
	<object>
		<name>car</name>
		<bndbox>
			<xmin>128</xmin>
			<ymax>509</ymax>
			<xmax>302</xmax>
			<ymin>412</ymin>
		</bndbox>
	</object>
	<object>
		<name>person</name>
		<bndbox>
			<xmin>150</xmin>
			<ymax>433</ymax>
			<xmax>186</xmax>
			<ymin>396</ymin>
		</bndbox>
	</object>
	<object>
		<name>car</name>
		<bndbox>
			<xmin>314</xmin>
			<ymax>503</ymax>
			<xmax>401</xmax>
			<ymin>403</ymin>
		</bndbox>
	</object>
	<object>
		<name>car</name>
		<bndbox>
			<xmin>4</xmin>
			<ymax>517</ymax>
			<xmax>157</xmax>
			<ymin>408</ymin>
		</bndbox>
	</object>
	<object>
		<name>person</name>
		<bndbox>
			<xmin>290</xmin>
			<ymax>525</ymax>
			<xmax>329</xmax>
			<ymin>418</ymin>
		</bndbox>
	</object>
	<object>
		<name>motorcycle</name>
		<bndbox>
			<xmin>1</xmin>
			<ymax>533</ymax>
			<xmax>73</xmax>
			<ymin>446</ymin>
		</bndbox>
	</object>
	<object>
		<name>rider</name>
		<bndbox>
			<xmin>12</xmin>
			<ymax>511</ymax>
			<xmax>62</xmax>
			<ymin>416</ymin>
		</bndbox>
	</object>
	<object>
		<name>rider</name>
		<bndbox>
			<xmin>1</xmin>
			<ymax>518</ymax>
			<xmax>57</xmax>
			<ymin>409</ymin>
		</bndbox>
	</object>
</annotation>