<?xml version="1.0" encoding="utf-8"?>
<annotation>
	<filename>0016020.jpg</filename>
	<folder>BLR-2018-04-19_17-56-55_frontFar_right_3</folder>
	<size>
		<width>1280</width>
		<height>964</height>
		<depth>3</depth>
	</size>
	<object>
		<name>person</name>
		<bndbox>
			<xmin>670</xmin>
			<ymax>422</ymax>
			<xmax>693</xmax>
			<ymin>386</ymin>
		</bndbox>
	</object>
	<object>
		<name>person</name>
		<bndbox>
			<xmin>708</xmin>
			<ymax>426</ymax>
			<xmax>728</xmax>
			<ymin>377</ymin>
		</bndbox>
	</object>
	<object>
		<name>person</name>
		<bndbox>
			<xmin>723</xmin>
			<ymax>422</ymax>
			<xmax>745</xmax>
			<ymin>386</ymin>
		</bndbox>
	</object>
	<object>
		<name>person</name>
		<bndbox>
			<xmin>772</xmin>
			<ymax>428</ymax>
			<xmax>787</xmax>
			<ymin>395</ymin>
		</bndbox>
	</object>
	<object>
		<name>person</name>
		<bndbox>
			<xmin>785</xmin>
			<ymax>426</ymax>
			<xmax>802</xmax>
			<ymin>381</ymin>
		</bndbox>
	</object>
	<object>
		<name>person</name>
		<bndbox>
			<xmin>830</xmin>
			<ymax>415</ymax>
			<xmax>852</xmax>
			<ymin>376</ymin>
		</bndbox>
	</object>
	<object>
		<name>person</name>
		<bndbox>
			<xmin>852</xmin>
			<ymax>418</ymax>
			<xmax>874</xmax>
			<ymin>376</ymin>
		</bndbox>
	</object>
	<object>
		<name>person</name>
		<bndbox>
			<xmin>902</xmin>
			<ymax>418</ymax>
			<xmax>924</xmax>
			<ymin>377</ymin>
		</bndbox>
	</object>
	<object>
		<name>person</name>
		<bndbox>
			<xmin>1045</xmin>
			<ymax>458</ymax>
			<xmax>1071</xmax>
			<ymin>403</ymin>
		</bndbox>
	</object>
	<object>
		<name>autorickshaw</name>
		<bndbox>
			<xmin>1057</xmin>
			<ymax>501</ymax>
			<xmax>1199</xmax>
			<ymin>364</ymin>
		</bndbox>
	</object>
	<object>
		<name>person</name>
		<bndbox>
			<xmin>936</xmin>
			<ymax>475</ymax>
			<xmax>972</xmax>
			<ymin>382</ymin>
		</bndbox>
	</object>
	<object>
		<name>person</name>
		<bndbox>
			<xmin>966</xmin>
			<ymax>476</ymax>
			<xmax>1007</xmax>
			<ymin>386</ymin>
		</bndbox>
	</object>
	<object>
		<name>motorcycle</name>
		<bndbox>
			<xmin>559</xmin>
			<ymax>457</ymax>
			<xmax>594</xmax>
			<ymin>410</ymin>
		</bndbox>
	</object>
	<object>
		<name>rider</name>
		<bndbox>
			<xmin>559</xmin>
			<ymax>450</ymax>
			<xmax>592</xmax>
			<ymin>395</ymin>
		</bndbox>
	</object>
	<object>
		<name>car</name>
		<bndbox>
			<xmin>247</xmin>
			<ymax>453</ymax>
			<xmax>319</xmax>
			<ymin>405</ymin>
		</bndbox>
	</object>
	<object>
		<name>vehicle fallback</name>
		<bndbox>
			<xmin>130</xmin>
			<ymax>481</ymax>
			<xmax>278</xmax>
			<ymin>374</ymin>
		</bndbox>
	</object>
	<object>
		<name>vehicle fallback</name>
		<bndbox>
			<xmin>2</xmin>
			<ymax>467</ymax>
			<xmax>144</xmax>
			<ymin>368</ymin>
		</bndbox>
	</object>
</annotation>