<?xml version="1.0" encoding="utf-8"?>
<annotation>
	<filename>0001053.jpg</filename>
	<folder>HYD-2018-08-05_13-02-17_2</folder>
	<size>
		<width>1920</width>
		<height>1080</height>
		<depth>3</depth>
	</size>
	<object>
		<name>truck</name>
		<bndbox>
			<xmin>722</xmin>
			<ymax>556</ymax>
			<xmax>782</xmax>
			<ymin>511</ymin>
		</bndbox>
	</object>
	<object>
		<name>person</name>
		<bndbox>
			<xmin>744</xmin>
			<ymax>576</ymax>
			<xmax>766</xmax>
			<ymin>545</ymin>
		</bndbox>
	</object>
	<object>
		<name>car</name>
		<bndbox>
			<xmin>648</xmin>
			<ymax>580</ymax>
			<xmax>728</xmax>
			<ymin>541</ymin>
		</bndbox>
	</object>
	<object>
		<name>car</name>
		<bndbox>
			<xmin>660</xmin>
			<ymax>577</ymax>
			<xmax>752</xmax>
			<ymin>552</ymin>
		</bndbox>
	</object>
	<object>
		<name>car</name>
		<bndbox>
			<xmin>755</xmin>
			<ymax>577</ymax>
			<xmax>815</xmax>
			<ymin>547</ymin>
		</bndbox>
	</object>
	<object>
		<name>rider</name>
		<bndbox>
			<xmin>804</xmin>
			<ymax>559</ymax>
			<xmax>817</xmax>
			<ymin>543</ymin>
		</bndbox>
	</object>
	<object>
		<name>person</name>
		<bndbox>
			<xmin>816</xmin>
			<ymax>551</ymax>
			<xmax>825</xmax>
			<ymin>540</ymin>
		</bndbox>
	</object>
	<object>
		<name>rider</name>
		<bndbox>
			<xmin>825</xmin>
			<ymax>578</ymax>
			<xmax>845</xmax>
			<ymin>544</ymin>
		</bndbox>
	</object>
	<object>
		<name>rider</name>
		<bndbox>
			<xmin>782</xmin>
			<ymax>578</ymax>
			<xmax>806</xmax>
			<ymin>541</ymin>
		</bndbox>
	</object>
	<object>
		<name>motorcycle</name>
		<bndbox>
			<xmin>780</xmin>
			<ymax>577</ymax>
			<xmax>818</xmax>
			<ymin>562</ymin>
		</bndbox>
	</object>
	<object>
		<name>person</name>
		<bndbox>
			<xmin>816</xmin>
			<ymax>577</ymax>
			<xmax>836</xmax>
			<ymin>551</ymin>
		</bndbox>
	</object>
	<object>
		<name>rider</name>
		<bndbox>
			<xmin>812</xmin>
			<ymax>566</ymax>
			<xmax>822</xmax>
			<ymin>549</ymin>
		</bndbox>
	</object>
	<object>
		<name>person</name>
		<bndbox>
			<xmin>801</xmin>
			<ymax>577</ymax>
			<xmax>819</xmax>
			<ymin>564</ymin>
		</bndbox>
	</object>
	<object>
		<name>person</name>
		<bndbox>
			<xmin>844</xmin>
			<ymax>630</ymax>
			<xmax>892</xmax>
			<ymin>545</ymin>
		</bndbox>
	</object>
	<object>
		<name>person</name>
		<bndbox>
			<xmin>889</xmin>
			<ymax>635</ymax>
			<xmax>922</xmax>
			<ymin>579</ymin>
		</bndbox>
	</object>
	<object>
		<name>rider</name>
		<bndbox>
			<xmin>893</xmin>
			<ymax>586</ymax>
			<xmax>917</xmax>
			<ymin>544</ymin>
		</bndbox>
	</object>
	<object>
		<name>rider</name>
		<bndbox>
			<xmin>894</xmin>
			<ymax>592</ymax>
			<xmax>929</xmax>
			<ymin>544</ymin>
		</bndbox>
	</object>
	<object>
		<name>motorcycle</name>
		<bndbox>
			<xmin>893</xmin>
			<ymax>610</ymax>
			<xmax>926</xmax>
			<ymin>573</ymin>
		</bndbox>
	</object>
	<object>
		<name>car</name>
		<bndbox>
			<xmin>845</xmin>
			<ymax>574</ymax>
			<xmax>904</xmax>
			<ymin>543</ymin>
		</bndbox>
	</object>
	<object>
		<name>car</name>
		<bndbox>
			<xmin>886</xmin>
			<ymax>586</ymax>
			<xmax>993</xmax>
			<ymin>539</ymin>
		</bndbox>
	</object>
	<object>
		<name>person</name>
		<bndbox>
			<xmin>949</xmin>
			<ymax>607</ymax>
			<xmax>979</xmax>
			<ymin>543</ymin>
		</bndbox>
	</object>
	<object>
		<name>person</name>
		<bndbox>
			<xmin>831</xmin>
			<ymax>833</ymax>
			<xmax>913</xmax>
			<ymin>581</ymin>
		</bndbox>
	</object>
	<object>
		<name>person</name>
		<bndbox>
			<xmin>902</xmin>
			<ymax>831</ymax>
			<xmax>1009</xmax>
			<ymin>568</ymin>
		</bndbox>
	</object>
	<object>
		<name>person</name>
		<bndbox>
			<xmin>634</xmin>
			<ymax>868</ymax>
			<xmax>755</xmax>
			<ymin>535</ymin>
		</bndbox>
	</object>
	<object>
		<name>person</name>
		<bndbox>
			<xmin>571</xmin>
			<ymax>858</ymax>
			<xmax>679</xmax>
			<ymin>583</ymin>
		</bndbox>
	</object>
	<object>
		<name>person</name>
		<bndbox>
			<xmin>496</xmin>
			<ymax>740</ymax>
			<xmax>577</xmax>
			<ymin>594</ymin>
		</bndbox>
	</object>
	<object>
		<name>person</name>
		<bndbox>
			<xmin>444</xmin>
			<ymax>754</ymax>
			<xmax>550</xmax>
			<ymin>604</ymin>
		</bndbox>
	</object>
	<object>
		<name>person</name>
		<bndbox>
			<xmin>395</xmin>
			<ymax>763</ymax>
			<xmax>477</xmax>
			<ymin>605</ymin>
		</bndbox>
	</object>
	<object>
		<name>person</name>
		<bndbox>
			<xmin>362</xmin>
			<ymax>767</ymax>
			<xmax>429</xmax>
			<ymin>634</ymin>
		</bndbox>
	</object>
	<object>
		<name>person</name>
		<bndbox>
			<xmin>319</xmin>
			<ymax>888</ymax>
			<xmax>403</xmax>
			<ymin>574</ymin>
		</bndbox>
	</object>
	<object>
		<name>person</name>
		<bndbox>
			<xmin>250</xmin>
			<ymax>951</ymax>
			<xmax>410</xmax>
			<ymin>552</ymin>
		</bndbox>
	</object>
	<object>
		<name>person</name>
		<bndbox>
			<xmin>192</xmin>
			<ymax>937</ymax>
			<xmax>350</xmax>
			<ymin>553</ymin>
		</bndbox>
	</object>
	<object>
		<name>person</name>
		<bndbox>
			<xmin>163</xmin>
			<ymax>899</ymax>
			<xmax>278</xmax>
			<ymin>587</ymin>
		</bndbox>
	</object>
	<object>
		<name>person</name>
		<bndbox>
			<xmin>44</xmin>
			<ymax>919</ymax>
			<xmax>178</xmax>
			<ymin>536</ymin>
		</bndbox>
	</object>
	<object>
		<name>motorcycle</name>
		<bndbox>
			<xmin>30</xmin>
			<ymax>882</ymax>
			<xmax>214</xmax>
			<ymin>644</ymin>
		</bndbox>
	</object>
	<object>
		<name>motorcycle</name>
		<bndbox>
			<xmin>1250</xmin>
			<ymax>568</ymax>
			<xmax>1273</xmax>
			<ymin>534</ymin>
		</bndbox>
	</object>
	<object>
		<name>motorcycle</name>
		<bndbox>
			<xmin>1152</xmin>
			<ymax>748</ymax>
			<xmax>1234</xmax>
			<ymin>590</ymin>
		</bndbox>
	</object>
	<object>
		<name>rider</name>
		<bndbox>
			<xmin>1181</xmin>
			<ymax>588</ymax>
			<xmax>1221</xmax>
			<ymin>556</ymin>
		</bndbox>
	</object>
	<object>
		<name>rider</name>
		<bndbox>
			<xmin>1152</xmin>
			<ymax>708</ymax>
			<xmax>1244</xmax>
			<ymin>558</ymin>
		</bndbox>
	</object>
	<object>
		<name>person</name>
		<bndbox>
			<xmin>1246</xmin>
			<ymax>718</ymax>
			<xmax>1307</xmax>
			<ymin>545</ymin>
		</bndbox>
	</object>
	<object>
		<name>autorickshaw</name>
		<bndbox>
			<xmin>1291</xmin>
			<ymax>575</ymax>
			<xmax>1343</xmax>
			<ymin>514</ymin>
		</bndbox>
	</object>
	<object>
		<name>bus</name>
		<bndbox>
			<xmin>1369</xmin>
			<ymax>568</ymax>
			<xmax>1559</xmax>
			<ymin>471</ymin>
		</bndbox>
	</object>
	<object>
		<name>truck</name>
		<bndbox>
			<xmin>1515</xmin>
			<ymax>568</ymax>
			<xmax>1670</xmax>
			<ymin>486</ymin>
		</bndbox>
	</object>
	<object>
		<name>person</name>
		<bndbox>
			<xmin>1554</xmin>
			<ymax>564</ymax>
			<xmax>1579</xmax>
			<ymin>521</ymin>
		</bndbox>
	</object>
	<object>
		<name>person</name>
		<bndbox>
			<xmin>1580</xmin>
			<ymax>568</ymax>
			<xmax>1615</xmax>
			<ymin>527</ymin>
		</bndbox>
	</object>
	<object>
		<name>person</name>
		<bndbox>
			<xmin>1608</xmin>
			<ymax>569</ymax>
			<xmax>1629</xmax>
			<ymin>530</ymin>
		</bndbox>
	</object>
	<object>
		<name>car</name>
		<bndbox>
			<xmin>1666</xmin>
			<ymax>559</ymax>
			<xmax>1725</xmax>
			<ymin>501</ymin>
		</bndbox>
	</object>
	<object>
		<name>person</name>
		<bndbox>
			<xmin>1501</xmin>
			<ymax>812</ymax>
			<xmax>1581</xmax>
			<ymin>561</ymin>
		</bndbox>
	</object>
	<object>
		<name>person</name>
		<bndbox>
			<xmin>1578</xmin>
			<ymax>933</ymax>
			<xmax>1733</xmax>
			<ymin>590</ymin>
		</bndbox>
	</object>
	<object>
		<name>person</name>
		<bndbox>
			<xmin>1705</xmin>
			<ymax>915</ymax>
			<xmax>1832</xmax>
			<ymin>574</ymin>
		</bndbox>
	</object>
	<object>
		<name>person</name>
		<bndbox>
			<xmin>1809</xmin>
			<ymax>897</ymax>
			<xmax>1920</xmax>
			<ymin>559</ymin>
		</bndbox>
	</object>
</annotation>