<?xml version="1.0" encoding="utf-8"?>
<annotation>
	<filename>0003795.jpg</filename>
	<folder>BLR-2018-05-22_12-24-44_sideRight_left_5</folder>
	<size>
		<width>1920</width>
		<height>1080</height>
		<depth>3</depth>
	</size>
	<object>
		<name>car</name>
		<bndbox>
			<xmin>1</xmin>
			<ymax>519</ymax>
			<xmax>169</xmax>
			<ymin>408</ymin>
		</bndbox>
	</object>
	<object>
		<name>rider</name>
		<bndbox>
			<xmin>308</xmin>
			<ymax>497</ymax>
			<xmax>372</xmax>
			<ymin>428</ymin>
		</bndbox>
	</object>
	<object>
		<name>motorcycle</name>
		<bndbox>
			<xmin>354</xmin>
			<ymax>519</ymax>
			<xmax>397</xmax>
			<ymin>494</ymin>
		</bndbox>
	</object>
	<object>
		<name>car</name>
		<bndbox>
			<xmin>1</xmin>
			<ymax>819</ymax>
			<xmax>498</xmax>
			<ymin>442</ymin>
		</bndbox>
	</object>
	<object>
		<name>autorickshaw</name>
		<bndbox>
			<xmin>476</xmin>
			<ymax>1080</ymax>
			<xmax>1624</xmax>
			<ymin>422</ymin>
		</bndbox>
	</object>
	<object>
		<name>motorcycle</name>
		<bndbox>
			<xmin>1624</xmin>
			<ymax>1070</ymax>
			<xmax>1916</xmax>
			<ymin>725</ymin>
		</bndbox>
	</object>
	<object>
		<name>rider</name>
		<bndbox>
			<xmin>1811</xmin>
			<ymax>1044</ymax>
			<xmax>1918</xmax>
			<ymin>592</ymin>
		</bndbox>
	</object>
</annotation>