<?xml version="1.0" encoding="utf-8"?>
<annotation>
	<filename>0002700.jpg</filename>
	<folder>BLR-2018-05-17_15-23-02_rearNear_left_4</folder>
	<size>
		<width>1920</width>
		<height>1080</height>
		<depth>3</depth>
	</size>
	<object>
		<name>motorcycle</name>
		<bndbox>
			<xmin>269</xmin>
			<ymax>600</ymax>
			<xmax>330</xmax>
			<ymin>514</ymin>
		</bndbox>
	</object>
	<object>
		<name>rider</name>
		<bndbox>
			<xmin>270</xmin>
			<ymax>576</ymax>
			<xmax>337</xmax>
			<ymin>482</ymin>
		</bndbox>
	</object>
	<object>
		<name>motorcycle</name>
		<bndbox>
			<xmin>413</xmin>
			<ymax>500</ymax>
			<xmax>435</xmax>
			<ymin>479</ymin>
		</bndbox>
	</object>
	<object>
		<name>rider</name>
		<bndbox>
			<xmin>415</xmin>
			<ymax>489</ymax>
			<xmax>434</xmax>
			<ymin>460</ymin>
		</bndbox>
	</object>
	<object>
		<name>motorcycle</name>
		<bndbox>
			<xmin>456</xmin>
			<ymax>495</ymax>
			<xmax>485</xmax>
			<ymin>473</ymin>
		</bndbox>
	</object>
	<object>
		<name>rider</name>
		<bndbox>
			<xmin>461</xmin>
			<ymax>489</ymax>
			<xmax>479</xmax>
			<ymin>459</ymin>
		</bndbox>
	</object>
	<object>
		<name>car</name>
		<bndbox>
			<xmin>533</xmin>
			<ymax>531</ymax>
			<xmax>638</xmax>
			<ymin>458</ymin>
		</bndbox>
	</object>
	<object>
		<name>car</name>
		<bndbox>
			<xmin>654</xmin>
			<ymax>566</ymax>
			<xmax>818</xmax>
			<ymin>443</ymin>
		</bndbox>
	</object>
	<object>
		<name>car</name>
		<bndbox>
			<xmin>728</xmin>
			<ymax>895</ymax>
			<xmax>1249</xmax>
			<ymin>453</ymin>
		</bndbox>
	</object>
	<object>
		<name>car</name>
		<bndbox>
			<xmin>76</xmin>
			<ymax>569</ymax>
			<xmax>233</xmax>
			<ymin>491</ymin>
		</bndbox>
	</object>
	<object>
		<name>car</name>
		<bndbox>
			<xmin>4</xmin>
			<ymax>583</ymax>
			<xmax>88</xmax>
			<ymin>500</ymin>
		</bndbox>
	</object>
	<object>
		<name>motorcycle</name>
		<bndbox>
			<xmin>7</xmin>
			<ymax>600</ymax>
			<xmax>114</xmax>
			<ymin>526</ymin>
		</bndbox>
	</object>
	<object>
		<name>rider</name>
		<bndbox>
			<xmin>27</xmin>
			<ymax>543</ymax>
			<xmax>51</xmax>
			<ymin>501</ymin>
		</bndbox>
	</object>
	<object>
		<name>rider</name>
		<bndbox>
			<xmin>50</xmin>
			<ymax>595</ymax>
			<xmax>94</xmax>
			<ymin>495</ymin>
		</bndbox>
	</object>
	<object>
		<name>car</name>
		<bndbox>
			<xmin>1</xmin>
			<ymax>1080</ymax>
			<xmax>367</xmax>
			<ymin>607</ymin>
		</bndbox>
	</object>
</annotation>