<?xml version="1.0" encoding="utf-8"?>
<annotation>
	<filename>0002580.jpg</filename>
	<folder>BLR-2018-06-05_08-39-44_rearNear_left_3</folder>
	<size>
		<width>1920</width>
		<height>1080</height>
		<depth>3</depth>
	</size>
	<object>
		<name>traffic sign</name>
		<bndbox>
			<xmin>902</xmin>
			<ymax>378</ymax>
			<xmax>923</xmax>
			<ymin>349</ymin>
		</bndbox>
	</object>
	<object>
		<name>traffic sign</name>
		<bndbox>
			<xmin>951</xmin>
			<ymax>374</ymax>
			<xmax>971</xmax>
			<ymin>343</ymin>
		</bndbox>
	</object>
	<object>
		<name>traffic sign</name>
		<bndbox>
			<xmin>1002</xmin>
			<ymax>381</ymax>
			<xmax>1030</xmax>
			<ymin>343</ymin>
		</bndbox>
	</object>
	<object>
		<name>person</name>
		<bndbox>
			<xmin>1151</xmin>
			<ymax>339</ymax>
			<xmax>1179</xmax>
			<ymin>310</ymin>
		</bndbox>
	</object>
	<object>
		<name>person</name>
		<bndbox>
			<xmin>1029</xmin>
			<ymax>394</ymax>
			<xmax>1057</xmax>
			<ymin>353</ymin>
		</bndbox>
	</object>
	<object>
		<name>traffic sign</name>
		<bndbox>
			<xmin>822</xmin>
			<ymax>365</ymax>
			<xmax>839</xmax>
			<ymin>352</ymin>
		</bndbox>
	</object>
	<object>
		<name>vehicle fallback</name>
		<bndbox>
			<xmin>66</xmin>
			<ymax>368</ymax>
			<xmax>239</xmax>
			<ymin>11</ymin>
		</bndbox>
	</object>
	<object>
		<name>bus</name>
		<bndbox>
			<xmin>258</xmin>
			<ymax>361</ymax>
			<xmax>393</xmax>
			<ymin>228</ymin>
		</bndbox>
	</object>
	<object>
		<name>bus</name>
		<bndbox>
			<xmin>382</xmin>
			<ymax>639</ymax>
			<xmax>825</xmax>
			<ymin>107</ymin>
		</bndbox>
	</object>
	<object>
		<name>bus</name>
		<bndbox>
			<xmin>1</xmin>
			<ymax>427</ymax>
			<xmax>70</xmax>
			<ymin>153</ymin>
		</bndbox>
	</object>
	<object>
		<name>car</name>
		<bndbox>
			<xmin>0</xmin>
			<ymax>640</ymax>
			<xmax>325</xmax>
			<ymin>321</ymin>
		</bndbox>
	</object>
	<object>
		<name>car</name>
		<bndbox>
			<xmin>1</xmin>
			<ymax>1077</ymax>
			<xmax>830</xmax>
			<ymin>306</ymin>
		</bndbox>
	</object>
	<object>
		<name>traffic sign</name>
		<bndbox>
			<xmin>1323</xmin>
			<ymax>767</ymax>
			<xmax>1409</xmax>
			<ymin>547</ymin>
		</bndbox>
	</object>
	<object>
		<name>traffic sign</name>
		<bndbox>
			<xmin>826</xmin>
			<ymax>415</ymax>
			<xmax>857</xmax>
			<ymin>368</ymin>
		</bndbox>
	</object>
</annotation>