<?xml version="1.0" encoding="utf-8"?>
<annotation>
	<filename>0003885.jpg</filename>
	<folder>BLR-2018-05-03_14-26-52_sideLeft_right_5</folder>
	<size>
		<width>1920</width>
		<height>1080</height>
		<depth>3</depth>
	</size>
	<object>
		<name>person</name>
		<bndbox>
			<xmin>793</xmin>
			<ymax>441</ymax>
			<xmax>825</xmax>
			<ymin>353</ymin>
		</bndbox>
	</object>
	<object>
		<name>person</name>
		<bndbox>
			<xmin>971</xmin>
			<ymax>411</ymax>
			<xmax>988</xmax>
			<ymin>339</ymin>
		</bndbox>
	</object>
	<object>
		<name>vehicle fallback</name>
		<bndbox>
			<xmin>1384</xmin>
			<ymax>373</ymax>
			<xmax>1417</xmax>
			<ymin>348</ymin>
		</bndbox>
	</object>
	<object>
		<name>person</name>
		<bndbox>
			<xmin>1425</xmin>
			<ymax>373</ymax>
			<xmax>1433</xmax>
			<ymin>349</ymin>
		</bndbox>
	</object>
	<object>
		<name>person</name>
		<bndbox>
			<xmin>1672</xmin>
			<ymax>376</ymax>
			<xmax>1677</xmax>
			<ymin>355</ymin>
		</bndbox>
	</object>
	<object>
		<name>person</name>
		<bndbox>
			<xmin>1667</xmin>
			<ymax>377</ymax>
			<xmax>1674</xmax>
			<ymin>355</ymin>
		</bndbox>
	</object>
	<object>
		<name>bus</name>
		<bndbox>
			<xmin>1830</xmin>
			<ymax>427</ymax>
			<xmax>1901</xmax>
			<ymin>324</ymin>
		</bndbox>
	</object>
	<object>
		<name>autorickshaw</name>
		<bndbox>
			<xmin>1804</xmin>
			<ymax>444</ymax>
			<xmax>1889</xmax>
			<ymin>367</ymin>
		</bndbox>
	</object>
	<object>
		<name>person</name>
		<bndbox>
			<xmin>1836</xmin>
			<ymax>451</ymax>
			<xmax>1858</xmax>
			<ymin>370</ymin>
		</bndbox>
	</object>
	<object>
		<name>bus</name>
		<bndbox>
			<xmin>1893</xmin>
			<ymax>463</ymax>
			<xmax>1920</xmax>
			<ymin>242</ymin>
		</bndbox>
	</object>
	<object>
		<name>motorcycle</name>
		<bndbox>
			<xmin>1705</xmin>
			<ymax>659</ymax>
			<xmax>1845</xmax>
			<ymin>446</ymin>
		</bndbox>
	</object>
	<object>
		<name>rider</name>
		<bndbox>
			<xmin>1753</xmin>
			<ymax>521</ymax>
			<xmax>1835</xmax>
			<ymin>384</ymin>
		</bndbox>
	</object>
	<object>
		<name>rider</name>
		<bndbox>
			<xmin>1690</xmin>
			<ymax>608</ymax>
			<xmax>1827</xmax>
			<ymin>383</ymin>
		</bndbox>
	</object>
	<object>
		<name>person</name>
		<bndbox>
			<xmin>1463</xmin>
			<ymax>461</ymax>
			<xmax>1500</xmax>
			<ymin>354</ymin>
		</bndbox>
	</object>
	<object>
		<name>person</name>
		<bndbox>
			<xmin>1133</xmin>
			<ymax>845</ymax>
			<xmax>1309</xmax>
			<ymin>365</ymin>
		</bndbox>
	</object>
	<object>
		<name>person</name>
		<bndbox>
			<xmin>741</xmin>
			<ymax>526</ymax>
			<xmax>809</xmax>
			<ymin>355</ymin>
		</bndbox>
	</object>
	<object>
		<name>person</name>
		<bndbox>
			<xmin>630</xmin>
			<ymax>754</ymax>
			<xmax>768</xmax>
			<ymin>375</ymin>
		</bndbox>
	</object>
	<object>
		<name>car</name>
		<bndbox>
			<xmin>720</xmin>
			<ymax>804</ymax>
			<xmax>1374</xmax>
			<ymin>379</ymin>
		</bndbox>
	</object>
	<object>
		<name>traffic sign</name>
		<bndbox>
			<xmin>1366</xmin>
			<ymax>296</ymax>
			<xmax>1409</xmax>
			<ymin>272</ymin>
		</bndbox>
	</object>
	<object>
		<name>traffic sign</name>
		<bndbox>
			<xmin>1578</xmin>
			<ymax>320</ymax>
			<xmax>1602</xmax>
			<ymin>302</ymin>
		</bndbox>
	</object>
</annotation>