<?xml version="1.0" encoding="utf-8"?>
<annotation>
	<filename>0000480.jpg</filename>
	<folder>BLR-2018-05-17_15-56-30_sideLeft_right_6</folder>
	<size>
		<width>1920</width>
		<height>1080</height>
		<depth>3</depth>
	</size>
	<object>
		<name>truck</name>
		<bndbox>
			<xmin>1739</xmin>
			<ymax>477</ymax>
			<xmax>1918</xmax>
			<ymin>268</ymin>
		</bndbox>
	</object>
	<object>
		<name>truck</name>
		<bndbox>
			<xmin>1522</xmin>
			<ymax>540</ymax>
			<xmax>1757</xmax>
			<ymin>319</ymin>
		</bndbox>
	</object>
	<object>
		<name>person</name>
		<bndbox>
			<xmin>1833</xmin>
			<ymax>494</ymax>
			<xmax>1899</xmax>
			<ymin>347</ymin>
		</bndbox>
	</object>
	<object>
		<name>motorcycle</name>
		<bndbox>
			<xmin>187</xmin>
			<ymax>436</ymax>
			<xmax>244</xmax>
			<ymin>347</ymin>
		</bndbox>
	</object>
	<object>
		<name>autorickshaw</name>
		<bndbox>
			<xmin>1</xmin>
			<ymax>1080</ymax>
			<xmax>109</xmax>
			<ymin>425</ymin>
		</bndbox>
	</object>
	<object>
		<name>motorcycle</name>
		<bndbox>
			<xmin>1442</xmin>
			<ymax>599</ymax>
			<xmax>1631</xmax>
			<ymin>408</ymin>
		</bndbox>
	</object>
</annotation>