<?xml version="1.0" encoding="utf-8"?>
<annotation>
	<filename>0007755.jpg</filename>
	<folder>BLR-2018-05-29_11-19-12_sideLeft_left_9</folder>
	<size>
		<width>1920</width>
		<height>1080</height>
		<depth>3</depth>
	</size>
	<object>
		<name>motorcycle</name>
		<bndbox>
			<xmin>1751</xmin>
			<ymax>743</ymax>
			<xmax>1920</xmax>
			<ymin>484</ymin>
		</bndbox>
	</object>
	<object>
		<name>rider</name>
		<bndbox>
			<xmin>1770</xmin>
			<ymax>704</ymax>
			<xmax>1916</xmax>
			<ymin>383</ymin>
		</bndbox>
	</object>
	<object>
		<name>motorcycle</name>
		<bndbox>
			<xmin>1473</xmin>
			<ymax>971</ymax>
			<xmax>1828</xmax>
			<ymin>500</ymin>
		</bndbox>
	</object>
	<object>
		<name>rider</name>
		<bndbox>
			<xmin>1542</xmin>
			<ymax>846</ymax>
			<xmax>1814</xmax>
			<ymin>397</ymin>
		</bndbox>
	</object>
	<object>
		<name>motorcycle</name>
		<bndbox>
			<xmin>676</xmin>
			<ymax>1080</ymax>
			<xmax>1502</xmax>
			<ymin>654</ymin>
		</bndbox>
	</object>
	<object>
		<name>rider</name>
		<bndbox>
			<xmin>944</xmin>
			<ymax>1072</ymax>
			<xmax>1442</xmax>
			<ymin>386</ymin>
		</bndbox>
	</object>
	<object>
		<name>bicycle</name>
		<bndbox>
			<xmin>60</xmin>
			<ymax>499</ymax>
			<xmax>138</xmax>
			<ymin>383</ymin>
		</bndbox>
	</object>
	<object>
		<name>bicycle</name>
		<bndbox>
			<xmin>43</xmin>
			<ymax>605</ymax>
			<xmax>167</xmax>
			<ymin>419</ymin>
		</bndbox>
	</object>
</annotation>