<?xml version="1.0" encoding="utf-8"?>
<annotation>
	<filename>0005505.jpg</filename>
	<folder>BLR-2018-05-11_13-42-30_sideLeft_right_7</folder>
	<size>
		<width>1920</width>
		<height>1080</height>
		<depth>3</depth>
	</size>
	<object>
		<name>traffic sign</name>
		<bndbox>
			<xmin>1385</xmin>
			<ymax>380</ymax>
			<xmax>1432</xmax>
			<ymin>316</ymin>
		</bndbox>
	</object>
	<object>
		<name>traffic sign</name>
		<bndbox>
			<xmin>1047</xmin>
			<ymax>296</ymax>
			<xmax>1142</xmax>
			<ymin>173</ymin>
		</bndbox>
	</object>
	<object>
		<name>car</name>
		<bndbox>
			<xmin>926</xmin>
			<ymax>548</ymax>
			<xmax>1173</xmax>
			<ymin>380</ymin>
		</bndbox>
	</object>
	<object>
		<name>car</name>
		<bndbox>
			<xmin>705</xmin>
			<ymax>578</ymax>
			<xmax>982</xmax>
			<ymin>388</ymin>
		</bndbox>
	</object>
	<object>
		<name>car</name>
		<bndbox>
			<xmin>409</xmin>
			<ymax>606</ymax>
			<xmax>747</xmax>
			<ymin>409</ymin>
		</bndbox>
	</object>
	<object>
		<name>car</name>
		<bndbox>
			<xmin>52</xmin>
			<ymax>661</ymax>
			<xmax>429</xmax>
			<ymin>408</ymin>
		</bndbox>
	</object>
	<object>
		<name>autorickshaw</name>
		<bndbox>
			<xmin>1666</xmin>
			<ymax>455</ymax>
			<xmax>1802</xmax>
			<ymin>373</ymin>
		</bndbox>
	</object>
	<object>
		<name>car</name>
		<bndbox>
			<xmin>1632</xmin>
			<ymax>543</ymax>
			<xmax>1804</xmax>
			<ymin>400</ymin>
		</bndbox>
	</object>
	<object>
		<name>motorcycle</name>
		<bndbox>
			<xmin>1826</xmin>
			<ymax>581</ymax>
			<xmax>1914</xmax>
			<ymin>447</ymin>
		</bndbox>
	</object>
	<object>
		<name>rider</name>
		<bndbox>
			<xmin>1817</xmin>
			<ymax>555</ymax>
			<xmax>1914</xmax>
			<ymin>377</ymin>
		</bndbox>
	</object>
</annotation>