<?xml version="1.0" encoding="utf-8"?>
<annotation>
	<filename>0001815.jpg</filename>
	<folder>BLR-2018-05-11_14-09-20_sideRight_right_4</folder>
	<size>
		<width>1920</width>
		<height>1080</height>
		<depth>3</depth>
	</size>
	<object>
		<name>person</name>
		<bndbox>
			<xmin>385</xmin>
			<ymax>479</ymax>
			<xmax>410</xmax>
			<ymin>409</ymin>
		</bndbox>
	</object>
	<object>
		<name>person</name>
		<bndbox>
			<xmin>409</xmin>
			<ymax>497</ymax>
			<xmax>438</xmax>
			<ymin>405</ymin>
		</bndbox>
	</object>
	<object>
		<name>person</name>
		<bndbox>
			<xmin>872</xmin>
			<ymax>545</ymax>
			<xmax>932</xmax>
			<ymin>434</ymin>
		</bndbox>
	</object>
	<object>
		<name>motorcycle</name>
		<bndbox>
			<xmin>1054</xmin>
			<ymax>634</ymax>
			<xmax>1216</xmax>
			<ymin>510</ymin>
		</bndbox>
	</object>
	<object>
		<name>rider</name>
		<bndbox>
			<xmin>1074</xmin>
			<ymax>601</ymax>
			<xmax>1153</xmax>
			<ymin>467</ymin>
		</bndbox>
	</object>
	<object>
		<name>rider</name>
		<bndbox>
			<xmin>1095</xmin>
			<ymax>575</ymax>
			<xmax>1150</xmax>
			<ymin>500</ymin>
		</bndbox>
	</object>
	<object>
		<name>motorcycle</name>
		<bndbox>
			<xmin>1860</xmin>
			<ymax>638</ymax>
			<xmax>1918</xmax>
			<ymin>497</ymin>
		</bndbox>
	</object>
	<object>
		<name>motorcycle</name>
		<bndbox>
			<xmin>133</xmin>
			<ymax>435</ymax>
			<xmax>149</xmax>
			<ymin>408</ymin>
		</bndbox>
	</object>
	<object>
		<name>motorcycle</name>
		<bndbox>
			<xmin>149</xmin>
			<ymax>437</ymax>
			<xmax>172</xmax>
			<ymin>409</ymin>
		</bndbox>
	</object>
	<object>
		<name>motorcycle</name>
		<bndbox>
			<xmin>27</xmin>
			<ymax>449</ymax>
			<xmax>54</xmax>
			<ymin>416</ymin>
		</bndbox>
	</object>
	<object>
		<name>motorcycle</name>
		<bndbox>
			<xmin>84</xmin>
			<ymax>487</ymax>
			<xmax>122</xmax>
			<ymin>426</ymin>
		</bndbox>
	</object>
	<object>
		<name>motorcycle</name>
		<bndbox>
			<xmin>52</xmin>
			<ymax>443</ymax>
			<xmax>68</xmax>
			<ymin>415</ymin>
		</bndbox>
	</object>
	<object>
		<name>rider</name>
		<bndbox>
			<xmin>24</xmin>
			<ymax>424</ymax>
			<xmax>49</xmax>
			<ymin>388</ymin>
		</bndbox>
	</object>
	<object>
		<name>rider</name>
		<bndbox>
			<xmin>86</xmin>
			<ymax>446</ymax>
			<xmax>118</xmax>
			<ymin>392</ymin>
		</bndbox>
	</object>
	<object>
		<name>rider</name>
		<bndbox>
			<xmin>44</xmin>
			<ymax>422</ymax>
			<xmax>63</xmax>
			<ymin>392</ymin>
		</bndbox>
	</object>
</annotation>