<?xml version="1.0" encoding="utf-8"?>
<annotation>
	<filename>0006405.jpg</filename>
	<folder>BLR-2018-06-05_08-39-44_frontNear_left_8</folder>
	<size>
		<width>1920</width>
		<height>1080</height>
		<depth>3</depth>
	</size>
	<object>
		<name>person</name>
		<bndbox>
			<xmin>1</xmin>
			<ymax>1080</ymax>
			<xmax>158</xmax>
			<ymin>656</ymin>
		</bndbox>
	</object>
	<object>
		<name>person</name>
		<bndbox>
			<xmin>259</xmin>
			<ymax>1065</ymax>
			<xmax>575</xmax>
			<ymin>514</ymin>
		</bndbox>
	</object>
	<object>
		<name>person</name>
		<bndbox>
			<xmin>953</xmin>
			<ymax>759</ymax>
			<xmax>1021</xmax>
			<ymin>530</ymin>
		</bndbox>
	</object>
	<object>
		<name>person</name>
		<bndbox>
			<xmin>880</xmin>
			<ymax>814</ymax>
			<xmax>995</xmax>
			<ymin>526</ymin>
		</bndbox>
	</object>
	<object>
		<name>person</name>
		<bndbox>
			<xmin>1099</xmin>
			<ymax>590</ymax>
			<xmax>1123</xmax>
			<ymin>555</ymin>
		</bndbox>
	</object>
	<object>
		<name>person</name>
		<bndbox>
			<xmin>1079</xmin>
			<ymax>638</ymax>
			<xmax>1108</xmax>
			<ymin>549</ymin>
		</bndbox>
	</object>
	<object>
		<name>person</name>
		<bndbox>
			<xmin>1083</xmin>
			<ymax>707</ymax>
			<xmax>1129</xmax>
			<ymin>571</ymin>
		</bndbox>
	</object>
	<object>
		<name>person</name>
		<bndbox>
			<xmin>1128</xmin>
			<ymax>632</ymax>
			<xmax>1155</xmax>
			<ymin>568</ymin>
		</bndbox>
	</object>
	<object>
		<name>motorcycle</name>
		<bndbox>
			<xmin>1120</xmin>
			<ymax>733</ymax>
			<xmax>1213</xmax>
			<ymin>604</ymin>
		</bndbox>
	</object>
	<object>
		<name>rider</name>
		<bndbox>
			<xmin>1134</xmin>
			<ymax>711</ymax>
			<xmax>1202</xmax>
			<ymin>561</ymin>
		</bndbox>
	</object>
	<object>
		<name>person</name>
		<bndbox>
			<xmin>1140</xmin>
			<ymax>598</ymax>
			<xmax>1158</xmax>
			<ymin>558</ymin>
		</bndbox>
	</object>
	<object>
		<name>bus</name>
		<bndbox>
			<xmin>1178</xmin>
			<ymax>629</ymax>
			<xmax>1239</xmax>
			<ymin>526</ymin>
		</bndbox>
	</object>
	<object>
		<name>bus</name>
		<bndbox>
			<xmin>1209</xmin>
			<ymax>673</ymax>
			<xmax>1320</xmax>
			<ymin>478</ymin>
		</bndbox>
	</object>
	<object>
		<name>bus</name>
		<bndbox>
			<xmin>1241</xmin>
			<ymax>1080</ymax>
			<xmax>1920</xmax>
			<ymin>1</ymin>
		</bndbox>
	</object>
</annotation>