<?xml version="1.0" encoding="utf-8"?>
<annotation>
	<filename>0004875.jpg</filename>
	<folder>BLR-2018-05-22_11-54-07_sideLeft_left_4</folder>
	<size>
		<width>1920</width>
		<height>1080</height>
		<depth>3</depth>
	</size>
	<object>
		<name>motorcycle</name>
		<bndbox>
			<xmin>1849</xmin>
			<ymax>454</ymax>
			<xmax>1886</xmax>
			<ymin>376</ymin>
		</bndbox>
	</object>
	<object>
		<name>person</name>
		<bndbox>
			<xmin>1872</xmin>
			<ymax>396</ymax>
			<xmax>1902</xmax>
			<ymin>354</ymin>
		</bndbox>
	</object>
	<object>
		<name>vehicle fallback</name>
		<bndbox>
			<xmin>1415</xmin>
			<ymax>640</ymax>
			<xmax>1856</xmax>
			<ymin>107</ymin>
		</bndbox>
	</object>
	<object>
		<name>person</name>
		<bndbox>
			<xmin>1860</xmin>
			<ymax>490</ymax>
			<xmax>1906</xmax>
			<ymin>370</ymin>
		</bndbox>
	</object>
	<object>
		<name>rider</name>
		<bndbox>
			<xmin>1333</xmin>
			<ymax>466</ymax>
			<xmax>1480</xmax>
			<ymin>200</ymin>
		</bndbox>
	</object>
	<object>
		<name>person</name>
		<bndbox>
			<xmin>965</xmin>
			<ymax>967</ymax>
			<xmax>1144</xmax>
			<ymin>380</ymin>
		</bndbox>
	</object>
	<object>
		<name>person</name>
		<bndbox>
			<xmin>1903</xmin>
			<ymax>472</ymax>
			<xmax>1920</xmax>
			<ymin>382</ymin>
		</bndbox>
	</object>
</annotation>