<?xml version="1.0" encoding="utf-8"?>
<annotation>
	<filename>0006120.jpg</filename>
	<folder>BLR-2018-03-22_17-39-26_3_sideRight_left_6</folder>
	<size>
		<width>1920</width>
		<height>1080</height>
		<depth>3</depth>
	</size>
	<object>
		<name>animal</name>
		<bndbox>
			<xmin>1335</xmin>
			<ymax>288</ymax>
			<xmax>1352</xmax>
			<ymin>272</ymin>
		</bndbox>
	</object>
	<object>
		<name>animal</name>
		<bndbox>
			<xmin>1183</xmin>
			<ymax>284</ymax>
			<xmax>1199</xmax>
			<ymin>270</ymin>
		</bndbox>
	</object>
	<object>
		<name>animal</name>
		<bndbox>
			<xmin>1161</xmin>
			<ymax>284</ymax>
			<xmax>1173</xmax>
			<ymin>273</ymin>
		</bndbox>
	</object>
	<object>
		<name>animal</name>
		<bndbox>
			<xmin>1151</xmin>
			<ymax>286</ymax>
			<xmax>1163</xmax>
			<ymin>275</ymin>
		</bndbox>
	</object>
	<object>
		<name>animal</name>
		<bndbox>
			<xmin>1125</xmin>
			<ymax>286</ymax>
			<xmax>1144</xmax>
			<ymin>272</ymin>
		</bndbox>
	</object>
	<object>
		<name>animal</name>
		<bndbox>
			<xmin>1116</xmin>
			<ymax>286</ymax>
			<xmax>1128</xmax>
			<ymin>271</ymin>
		</bndbox>
	</object>
</annotation>