<?xml version="1.0" encoding="utf-8"?>
<annotation>
	<filename>0017280.jpg</filename>
	<folder>BLR-2018-04-19_17-16-55_frontFar_left_9</folder>
	<size>
		<width>1280</width>
		<height>964</height>
		<depth>3</depth>
	</size>
	<object>
		<name>traffic sign</name>
		<bndbox>
			<xmin>263</xmin>
			<ymax>747</ymax>
			<xmax>305</xmax>
			<ymin>670</ymin>
		</bndbox>
	</object>
	<object>
		<name>car</name>
		<bndbox>
			<xmin>853</xmin>
			<ymax>497</ymax>
			<xmax>898</xmax>
			<ymin>452</ymin>
		</bndbox>
	</object>
	<object>
		<name>traffic sign</name>
		<bndbox>
			<xmin>1185</xmin>
			<ymax>612</ymax>
			<xmax>1210</xmax>
			<ymin>557</ymin>
		</bndbox>
	</object>
</annotation>